oss2_uploader/__init__.py
oss2_uploader/main.py
oss2_uploader-0.1.0.dist-info/METADATA
oss2_uploader-0.1.0.dist-info/WHEEL
oss2_uploader-0.1.0.dist-info/licenses/LICENSE
oss2_uploader-0.1.0.dist-info/RECORD
